README.md
setup.cfg
setup.py
django_gsheets_roymo.egg-info/PKG-INFO
django_gsheets_roymo.egg-info/SOURCES.txt
django_gsheets_roymo.egg-info/dependency_links.txt
django_gsheets_roymo.egg-info/requires.txt
django_gsheets_roymo.egg-info/top_level.txt
gsheets/__init__.py
gsheets/admin.py
gsheets/apps.py
gsheets/auth.py
gsheets/decorators.py
gsheets/gsheets.py
gsheets/mixins.py
gsheets/models.py
gsheets/settings.py
gsheets/tests.py
gsheets/urls.py
gsheets/views.py
gsheets/management/__init__.py
gsheets/management/commands/__init__.py
gsheets/management/commands/syncgsheets.py
gsheets/migrations/0001_initial.py
gsheets/migrations/0002_accesscredentials_created_time.py
gsheets/migrations/__init__.py
gsheets/signals/__init__.py