Metadata-Version: 2.1
Name: django-gsheets-roymo
Version: 0.0.9.1
Summary: Fork of django-gsheets
Home-page: https://github.com/Rommel-Montgomery/django-gsheets
Author: Bobby Steinbach
Author-email: developers@meanpug.com
License: UNKNOWN
Keywords: roymo
Platform: UNKNOWN
Classifier: Programming Language :: Python :: 3
Classifier: License :: OSI Approved :: MIT License
Classifier: Operating System :: OS Independent
Requires-Python: >=3
